{"diff_netsenders_30": 5, "diff_netsenders_365": 6, "diff_netsenders_7": -2, "diff_netsent_30": 19, "diff_netsent_365": 21, "diff_netsent_7": -4, "first_date": "2015-09-11", "last_date": "2015-10-10", "percentage_senders_30": 500, "percentage_senders_365": 0, "percentage_senders_7": 66, "percentage_sent_30": 1900, "percentage_sent_365": 0, "percentage_sent_7": 80, "repositories": 1, "senders": 1, "senders_30": 6, "senders_365": 6, "senders_7": 1, "senders_init": 0, "senders_response": 1, "sent": 12, "sent_30": 20, "sent_365": 21, "sent_7": 1, "sent_response": 12, "threads": 0}