{"diff_netsenders_30": 2, "diff_netsenders_365": 7, "diff_netsenders_7": -4, "diff_netsent_30": 115, "diff_netsent_365": 125, "diff_netsent_7": 44, "first_date": "2015-09-06", "last_date": "2015-10-15", "percentage_senders_30": 50, "percentage_senders_365": 0, "percentage_senders_7": 80, "percentage_sent_30": 2300, "percentage_sent_365": 0, "percentage_sent_7": 275, "repositories": 1, "senders": 7, "senders_30": 6, "senders_365": 7, "senders_7": 1, "senders_init": 6, "senders_response": 6, "sent": 125, "sent_30": 120, "sent_365": 125, "sent_7": 60, "sent_response": 96, "threads": 29}